<ml:widget xmlns="http://www.w3.org/1999/xhtml" xmlns:ml="http://developer.marklogic.com/site/internal">
  <h1><img src="/images/i_book.png" alt="" width="24" height="22" /> New Tutorials!</h1>
  <div>
    <ul>
      <li><a href="/try/java/index">The Java API in 5 minutes</a></li>
      <li><a href="/try/rest/index">The REST API in 5 minutes</a></li>
      <li><a href="/learn/java">Learning the MarkLogic Java API</a></li>
      <li><a href="/learn/rest">Learning the MarkLogic REST API</a></li>
    </ul>
  </div>
</ml:widget>
